ak_requests/__init__.py
ak_requests/beautifulsoup.py
ak_requests/logger.py
ak_requests/request.py
ak_requests-0.1.1.dist-info/LICENSE
ak_requests-0.1.1.dist-info/WHEEL
ak_requests-0.1.1.dist-info/METADATA
ak_requests-0.1.1.dist-info/RECORD
