Metadata-Version: 2.1
Name: ak_requests
Version: 0.1.1
Summary: Requests package with QOL improvements and anti-bot detection measures
Author-email: Arun Kishore <pypi@rpakishore.co.in>
Requires-Python: >=3.11.0
Classifier: License :: OSI Approved :: MIT License
Requires-Dist: requests>=2.31.0
Requires-Dist: beautifulsoup4>=4.12.2
Requires-Dist: yt-dlp>=2023.10.13
Requires-Dist: ipykernel ; extra == "dev"
Requires-Dist: pytest>=7.4.3 ; extra == "test"
Project-URL: Home, https://github.com/rpakishore/ak_requests
Provides-Extra: dev
Provides-Extra: test
